pyspaceapis/__init__.py
pyspaceapis/debugtools.py
pyspaceapis/nasa.py
pyspaceapis-0.6.0.dist-info/licenses/LICENSE.txt
pyspaceapis-0.6.0.dist-info/METADATA
pyspaceapis-0.6.0.dist-info/WHEEL
pyspaceapis-0.6.0.dist-info/top_level.txt
pyspaceapis-0.6.0.dist-info/RECORD
