Metadata-Version: 2.4
Name: pyspaceapis
Version: 0.6.0
Summary: A Python API Wrapper for retrieving astronomical data from multiple APIs and endpoints!
Author: Kat (Py-Kat)
Author-email: imhelvetika@gmail.com
License-Expression: MIT
Project-URL: Homepage, https://github.com/Py-Kat/py-space-apis
Keywords: space,api,multi-api,wrapper,data
Classifier: Development Status :: 3 - Alpha
Classifier: Intended Audience :: Developers
Classifier: Natural Language :: English
Classifier: Programming Language :: Python :: 3
Classifier: Programming Language :: Python :: 3.11
Classifier: Programming Language :: Python :: 3.12
Classifier: Programming Language :: Python :: 3.13
Classifier: Topic :: Software Development :: Libraries :: Python Modules
Classifier: Topic :: Scientific/Engineering :: Astronomy
Classifier: Topic :: Internet :: WWW/HTTP
License-File: LICENSE.txt
Requires-Dist: requests~=2.32
Dynamic: license-file
